LICENSE.md
MANIFEST.in
README.md
VERSION
setup.py
bin/iceberg_rivers.mosaic
bin/iceberg_rivers.predict
bin/iceberg_rivers.tiling
src/iceberg_rivers/__init__.py
src/iceberg_rivers.search.egg-info/PKG-INFO
src/iceberg_rivers.search.egg-info/SOURCES.txt
src/iceberg_rivers.search.egg-info/dependency_links.txt
src/iceberg_rivers.search.egg-info/namespace_packages.txt
src/iceberg_rivers.search.egg-info/not-zip-safe
src/iceberg_rivers.search.egg-info/requires.txt
src/iceberg_rivers.search.egg-info/top_level.txt
src/iceberg_rivers/search/__init__.py
src/iceberg_rivers/search/classification/__init__.py
src/iceberg_rivers/search/classification/gen_patches.py
src/iceberg_rivers/search/classification/model.py
src/iceberg_rivers/search/classification/predict_unet.py
src/iceberg_rivers/search/classification/train_unet.py
src/iceberg_rivers/search/classification/unet_model.py
src/iceberg_rivers/search/mosaic/__init__.py
src/iceberg_rivers/search/mosaic/mosaic_unet.py
src/iceberg_rivers/search/tiling/__init__.py
src/iceberg_rivers/search/tiling/tile_unet.py
src/iceberg_rivers/search/training/__init__.py
src/iceberg_rivers/search/training/gen_patches.py
src/iceberg_rivers/search/training/mosaic_unet.py
src/iceberg_rivers/search/training/predict.py
src/iceberg_rivers/search/training/tile_predict_mosaic.py
src/iceberg_rivers/search/training/train_unet.py
src/iceberg_rivers/search/training/unet_model.py