Metadata-Version: 2.1
Name: iceberg-rivers.search
Version: 0.1.5
Summary: The ICEBERG Rivers usecase package
Home-page: https://www.github.com/iceberg-project/rivers/
Author: ICEBERG Team
Author-email: iceberg-ci@googlegroups.com
License: MIT
Platform: UNKNOWN
Classifier: Development Status :: 1 - Planning
Classifier: Intended Audience :: Developers
Classifier: Environment :: Console
Classifier: Programming Language :: Python
Classifier: Programming Language :: Python :: 3
Classifier: Programming Language :: Python :: 3.6
Classifier: Topic :: Utilities
Classifier: Topic :: Scientific/Engineering
Classifier: Operating System :: MacOS :: MacOS X
Classifier: Operating System :: POSIX
Classifier: Operating System :: Unix
